mpr_tools/__init__.py
mpr_tools/files/__init__.py
mpr_tools/files/ext.py
mpr_tools/files/loaders.py
mpr_tools-1.0.2.dist-info/METADATA
mpr_tools-1.0.2.dist-info/WHEEL
mpr_tools-1.0.2.dist-info/RECORD
